installcheck/__init__.py
installcheck/checker.py
installcheck/cli.py
installcheck/reporter.py
installcheck/utils.py
installcheck-0.1.0.dist-info/licenses/LICENSE
installcheck-0.1.0.dist-info/METADATA
installcheck-0.1.0.dist-info/WHEEL
installcheck-0.1.0.dist-info/entry_points.txt
installcheck-0.1.0.dist-info/top_level.txt
installcheck-0.1.0.dist-info/RECORD
