Metadata-Version: 2.4
Name: installcheck
Version: 0.1.0
Summary: CLI tool to check Python import dependencies in .py files
Author-email: Seong-hun Kim <kshoon92@gmail.com>
License: MIT
Project-URL: Homepage, https://github.com/seong-hun/installcheck
Project-URL: Bug Tracker, https://github.com/seong-hun/installcheck/issues
Keywords: import,dependency,checker,python,cli,lint
Classifier: Development Status :: 4 - Beta
Classifier: Intended Audience :: Developers
Classifier: License :: OSI Approved :: MIT License
Classifier: Operating System :: OS Independent
Classifier: Programming Language :: Python :: 3
Classifier: Programming Language :: Python :: 3.8
Classifier: Programming Language :: Python :: 3.9
Classifier: Programming Language :: Python :: 3.10
Classifier: Programming Language :: Python :: 3.11
Classifier: Topic :: Software Development :: Quality Assurance
Classifier: Topic :: Utilities
Requires-Python: >=3.8
License-File: LICENSE
Dynamic: license-file
